LICENSE.md
typegraph/__init__.py
typegraph/deploy/request.py
typegraph/effects.py
typegraph/envs/cli.py
typegraph/g.py
typegraph/gen/__init__.py
typegraph/gen/exports/__init__.py
typegraph/gen/exports/aws.py
typegraph/gen/exports/core.py
typegraph/gen/exports/runtimes.py
typegraph/gen/exports/utils.py
typegraph/gen/imports/__init__.py
typegraph/gen/imports/host.py
typegraph/gen/intrinsics.py
typegraph/gen/root.core0.wasm
typegraph/gen/root.core1.wasm
typegraph/gen/root.core2.wasm
typegraph/gen/types.py
typegraph/graph/metagen.py
typegraph/graph/params.py
typegraph/graph/shared_types.py
typegraph/graph/tg_artifact_upload.py
typegraph/graph/tg_deploy.py
typegraph/graph/tg_manage.py
typegraph/graph/typegraph.py
typegraph/host/host.py
typegraph/injection.py
typegraph/io.py
typegraph/policy.py
typegraph/providers/__init__.py
typegraph/providers/aws.py
typegraph/providers/prisma.py
typegraph/providers/temporal.py
typegraph/runtimes/__init__.py
typegraph/runtimes/base.py
typegraph/runtimes/deno.py
typegraph/runtimes/graphql.py
typegraph/runtimes/grpc.py
typegraph/runtimes/http.py
typegraph/runtimes/kv.py
typegraph/runtimes/python.py
typegraph/runtimes/random.py
typegraph/runtimes/substantial.py
typegraph/runtimes/wasm.py
typegraph/t.py
typegraph/utils.py
typegraph/wit.py
typegraph-0.5.0.dist-info/LICENSE.md
typegraph-0.5.0.dist-info/METADATA
typegraph-0.5.0.dist-info/WHEEL
typegraph-0.5.0.dist-info/RECORD
