Metadata-Version: 2.1
Name: typegraph
Version: 0.5.0
Summary: Declarative API development platform. Build backend components with WASM, Typescript and Python, no matter where and how your (legacy) systems are.
Home-page: https://metatype.dev
License: MPL-2.0
Keywords: api,composition,typesystem,graphql,ecosystem
Author: Metatype Contributors
Author-email: support@metatype.dev
Requires-Python: >=3.9,<4.0
Classifier: License :: OSI Approved
Classifier: Programming Language :: Python
Classifier: Programming Language :: Python :: 3
Classifier: Programming Language :: Python :: 3.9
Classifier: Programming Language :: Python :: 3.10
Classifier: Programming Language :: Python :: 3.11
Classifier: Programming Language :: Python :: 3.12
Classifier: Topic :: Software Development :: Libraries :: Python Modules
Requires-Dist: astunparse (>=1.6.3,<2.0.0)
Requires-Dist: python-box (>=7.1.1,<8.0.0)
Requires-Dist: typing-extensions (>=4.8.0,<5.0.0)
Requires-Dist: wasmtime (>=25.0.0,<26.0.0)
Project-URL: Repository, https://github.com/metatypedev/metatype
